eot_tools/__init__.py
eot_tools/eot.py
eot_tools/py.typed
eot_tools-0.1.0.dist-info/licenses/LICENSE.txt
eot_tools-0.1.0.dist-info/METADATA
eot_tools-0.1.0.dist-info/WHEEL
eot_tools-0.1.0.dist-info/top_level.txt
eot_tools-0.1.0.dist-info/RECORD
