Metadata-Version: 2.4
Name: eot_tools
Version: 0.1.0
Summary: Tools for working with EOT (Embedded OpenType) font files
Author: stefan6419846
License-Expression: MIT
Project-URL: Homepage, https://github.com/stefan6419846/eot_tools
Project-URL: Repository, https://github.com/stefan6419846/eot_tools
Project-URL: Issues, https://github.com/stefan6419846/eot_tools/issues
Project-URL: Changelog, https://github.com/stefan6419846/eot_tools/blob/main/CHANGELOG.md
Keywords: eot,font
Classifier: Development Status :: 4 - Beta
Classifier: Environment :: Console
Classifier: Intended Audience :: Developers
Classifier: Programming Language :: Python :: 3
Classifier: Programming Language :: Python :: 3 :: Only
Classifier: Topic :: Software Development
Classifier: Topic :: Text Processing :: Fonts
Classifier: Topic :: Utilities
Classifier: Typing :: Typed
Requires-Python: <4,>=3.9
License-File: LICENSE.txt
Provides-Extra: dev
Requires-Dist: codespell; extra == "dev"
Requires-Dist: coverage; extra == "dev"
Requires-Dist: flake8; extra == "dev"
Requires-Dist: flake8-bugbear; extra == "dev"
Requires-Dist: pep8-naming; extra == "dev"
Requires-Dist: mypy; extra == "dev"
Requires-Dist: fonttools; extra == "dev"
Dynamic: license-file
